<?xml version="1.0" encoding="utf-8"?>
<!DOCTYPE hibernate-mapping PUBLIC "-//Hibernate/Hibernate Mapping DTD 3.0//EN"
"http://hibernate.sourceforge.net/hibernate-mapping-3.0.dtd">
<!-- 
    Mapping file autogenerated by MyEclipse Persistence Tools
-->
<hibernate-mapping>
    <class name="co.com.coomeva.ele.entidades.planchas.dosmildoce.EleAsocSancionados5Annos" table="ELE_ASOC_SANCIONADOS_5_ANNOS" schema="ELECDB">
        <id name="codigoAsociado" type="java.lang.Long">
            <column name="NUMERO_DOCUMENTO" precision="17" scale="0" />
            <generator class="assigned" />
        </id>
        <property name="fechaRegistro" type="java.sql.Date">
            <column name="FECHA_REGISTRO" length="26" not-null="true" />
        </property>
        <property name="usuario" type="java.lang.String">
            <column name="USUARIO" length="10" not-null="true" />
        </property>
        <property name="fechaSuspension" type="java.sql.Date">
            <column name="FECHA_SUSPENSION" length="26" not-null="true" />
        </property>
        <property name="motivo" type="java.lang.String">
            <column name="MOTIVO_SUSPENSION" length="100" not-null="true" />
        </property>
    </class>
</hibernate-mapping>
